crhc_cli/__init__.py
crhc_cli/crhc.py
crhc_cli/conf/__init__.py
crhc_cli/conf/conf.py
crhc_cli/credential/__init__.py
crhc_cli/credential/credential.py
crhc_cli/credential/token.py
crhc_cli/execution/__init__.py
crhc_cli/execution/execution.py
crhc_cli/help/__init__.py
crhc_cli/help/help_opt.py
crhc_cli/parse/__init__.py
crhc_cli/parse/parse.py
crhc_cli/report/__init__.py
crhc_cli/report/report.py
crhc_cli/troubleshoot/__init__.py
crhc_cli/troubleshoot/ts.py
crhc_cli-1.16.16.data/scripts/crhc-cli
tests/__init__.py
tests/test_help.py
tests/test_report.py
crhc_cli-1.16.16.dist-info/LICENSE
crhc_cli-1.16.16.dist-info/METADATA
crhc_cli-1.16.16.dist-info/WHEEL
crhc_cli-1.16.16.dist-info/top_level.txt
crhc_cli-1.16.16.dist-info/RECORD
